{
  "formatVersion": 1,
  "nodes": [
    {
      "id": "0",
      "name": "Water",
      "children": [
        {
          "id": "6",
          "name": "Column",
          "children": [
            {
              "id": "1",
              "name": "Water",
              "children": [],
              "components": [
                {
                  "type": "TileMapRenderer",
                  "config": {
                    "tileMapAssetId": "117",
                    "tileSetAssetId": null,
                    "castShadow": false,
                    "receiveShadow": false,
                    "materialType": "basic",
                    "shaderAssetId": null
                  },
                  "id": "0"
                }
              ],
              "position": {
                "x": 0,
                "y": 0,
                "z": 0
              },
              "orientation": {
                "x": 0,
                "y": 0,
                "z": 0,
                "w": 1
              },
              "scale": {
                "x": 1,
                "y": 1,
                "z": 1
              },
              "visible": true,
              "layer": 0,
              "prefab": null
            },
            {
              "id": "2",
              "name": "Water1",
              "children": [],
              "components": [
                {
                  "type": "TileMapRenderer",
                  "config": {
                    "tileMapAssetId": "118",
                    "tileSetAssetId": null,
                    "castShadow": false,
                    "receiveShadow": false,
                    "materialType": "basic",
                    "shaderAssetId": null
                  },
                  "id": "0"
                }
              ],
              "position": {
                "x": 0,
                "y": 2,
                "z": 0
              },
              "orientation": {
                "x": 0,
                "y": 0,
                "z": 0,
                "w": 1
              },
              "scale": {
                "x": 1,
                "y": 1,
                "z": 1
              },
              "visible": true,
              "layer": 0,
              "prefab": null
            },
            {
              "id": "3",
              "name": "Water",
              "children": [],
              "components": [
                {
                  "type": "TileMapRenderer",
                  "config": {
                    "tileMapAssetId": "117",
                    "tileSetAssetId": null,
                    "castShadow": false,
                    "receiveShadow": false,
                    "materialType": "basic",
                    "shaderAssetId": null
                  },
                  "id": "0"
                }
              ],
              "position": {
                "x": 0,
                "y": -2,
                "z": 0
              },
              "orientation": {
                "x": 0,
                "y": 0,
                "z": 0,
                "w": 1
              },
              "scale": {
                "x": 1,
                "y": 1,
                "z": 1
              },
              "visible": true,
              "layer": 0,
              "prefab": null
            },
            {
              "id": "4",
              "name": "Water",
              "children": [],
              "components": [
                {
                  "type": "TileMapRenderer",
                  "config": {
                    "tileMapAssetId": "117",
                    "tileSetAssetId": null,
                    "castShadow": false,
                    "receiveShadow": false,
                    "materialType": "basic",
                    "shaderAssetId": null
                  },
                  "id": "0"
                }
              ],
              "position": {
                "x": 0,
                "y": -4,
                "z": 0
              },
              "orientation": {
                "x": 0,
                "y": 0,
                "z": 0,
                "w": 1
              },
              "scale": {
                "x": 1,
                "y": 1,
                "z": 1
              },
              "visible": true,
              "layer": 0,
              "prefab": null
            },
            {
              "id": "5",
              "name": "Water",
              "children": [],
              "components": [
                {
                  "type": "TileMapRenderer",
                  "config": {
                    "tileMapAssetId": "117",
                    "tileSetAssetId": null,
                    "castShadow": false,
                    "receiveShadow": false,
                    "materialType": "basic",
                    "shaderAssetId": null
                  },
                  "id": "0"
                }
              ],
              "position": {
                "x": 0,
                "y": -6,
                "z": 0
              },
              "orientation": {
                "x": 0,
                "y": 0,
                "z": 0,
                "w": 1
              },
              "scale": {
                "x": 1,
                "y": 1,
                "z": 1
              },
              "visible": true,
              "layer": 0,
              "prefab": null
            }
          ],
          "components": [],
          "position": {
            "x": 0,
            "y": 0,
            "z": 0
          },
          "orientation": {
            "x": 0,
            "y": 0,
            "z": 0,
            "w": 1
          },
          "scale": {
            "x": 1,
            "y": 1,
            "z": 1
          },
          "visible": true,
          "layer": 0,
          "prefab": null
        },
        {
          "id": "7",
          "name": "Column",
          "children": [
            {
              "id": "8",
              "name": "Water",
              "children": [],
              "components": [
                {
                  "type": "TileMapRenderer",
                  "config": {
                    "tileMapAssetId": "117",
                    "tileSetAssetId": null,
                    "castShadow": false,
                    "receiveShadow": false,
                    "materialType": "basic",
                    "shaderAssetId": null
                  },
                  "id": "0"
                }
              ],
              "position": {
                "x": 0,
                "y": 0,
                "z": 0
              },
              "orientation": {
                "x": 0,
                "y": 0,
                "z": 0,
                "w": 1
              },
              "scale": {
                "x": 1,
                "y": 1,
                "z": 1
              },
              "visible": true,
              "layer": 0,
              "prefab": null
            },
            {
              "id": "9",
              "name": "Water1",
              "children": [],
              "components": [
                {
                  "type": "TileMapRenderer",
                  "config": {
                    "tileMapAssetId": "118",
                    "tileSetAssetId": null,
                    "castShadow": false,
                    "receiveShadow": false,
                    "materialType": "basic",
                    "shaderAssetId": null
                  },
                  "id": "0"
                }
              ],
              "position": {
                "x": 0,
                "y": 2,
                "z": 0
              },
              "orientation": {
                "x": 0,
                "y": 0,
                "z": 0,
                "w": 1
              },
              "scale": {
                "x": 1,
                "y": 1,
                "z": 1
              },
              "visible": true,
              "layer": 0,
              "prefab": null
            },
            {
              "id": "10",
              "name": "Water",
              "children": [],
              "components": [
                {
                  "type": "TileMapRenderer",
                  "config": {
                    "tileMapAssetId": "117",
                    "tileSetAssetId": null,
                    "castShadow": false,
                    "receiveShadow": false,
                    "materialType": "basic",
                    "shaderAssetId": null
                  },
                  "id": "0"
                }
              ],
              "position": {
                "x": 0,
                "y": -2,
                "z": 0
              },
              "orientation": {
                "x": 0,
                "y": 0,
                "z": 0,
                "w": 1
              },
              "scale": {
                "x": 1,
                "y": 1,
                "z": 1
              },
              "visible": true,
              "layer": 0,
              "prefab": null
            },
            {
              "id": "11",
              "name": "Water",
              "children": [],
              "components": [
                {
                  "type": "TileMapRenderer",
                  "config": {
                    "tileMapAssetId": "117",
                    "tileSetAssetId": null,
                    "castShadow": false,
                    "receiveShadow": false,
                    "materialType": "basic",
                    "shaderAssetId": null
                  },
                  "id": "0"
                }
              ],
              "position": {
                "x": 0,
                "y": -4,
                "z": 0
              },
              "orientation": {
                "x": 0,
                "y": 0,
                "z": 0,
                "w": 1
              },
              "scale": {
                "x": 1,
                "y": 1,
                "z": 1
              },
              "visible": true,
              "layer": 0,
              "prefab": null
            },
            {
              "id": "12",
              "name": "Water",
              "children": [],
              "components": [
                {
                  "type": "TileMapRenderer",
                  "config": {
                    "tileMapAssetId": "117",
                    "tileSetAssetId": null,
                    "castShadow": false,
                    "receiveShadow": false,
                    "materialType": "basic",
                    "shaderAssetId": null
                  },
                  "id": "0"
                }
              ],
              "position": {
                "x": 0,
                "y": -6,
                "z": 0
              },
              "orientation": {
                "x": 0,
                "y": 0,
                "z": 0,
                "w": 1
              },
              "scale": {
                "x": 1,
                "y": 1,
                "z": 1
              },
              "visible": true,
              "layer": 0,
              "prefab": null
            }
          ],
          "components": [],
          "position": {
            "x": 2,
            "y": 0,
            "z": 0
          },
          "orientation": {
            "x": 0,
            "y": 0,
            "z": 0,
            "w": 1
          },
          "scale": {
            "x": 1,
            "y": 1,
            "z": 1
          },
          "visible": true,
          "layer": 0,
          "prefab": null
        },
        {
          "id": "13",
          "name": "Column",
          "children": [
            {
              "id": "14",
              "name": "Water",
              "children": [],
              "components": [
                {
                  "type": "TileMapRenderer",
                  "config": {
                    "tileMapAssetId": "117",
                    "tileSetAssetId": null,
                    "castShadow": false,
                    "receiveShadow": false,
                    "materialType": "basic",
                    "shaderAssetId": null
                  },
                  "id": "0"
                }
              ],
              "position": {
                "x": 0,
                "y": 0,
                "z": 0
              },
              "orientation": {
                "x": 0,
                "y": 0,
                "z": 0,
                "w": 1
              },
              "scale": {
                "x": 1,
                "y": 1,
                "z": 1
              },
              "visible": true,
              "layer": 0,
              "prefab": null
            },
            {
              "id": "15",
              "name": "Water1",
              "children": [],
              "components": [
                {
                  "type": "TileMapRenderer",
                  "config": {
                    "tileMapAssetId": "118",
                    "tileSetAssetId": null,
                    "castShadow": false,
                    "receiveShadow": false,
                    "materialType": "basic",
                    "shaderAssetId": null
                  },
                  "id": "0"
                }
              ],
              "position": {
                "x": 0,
                "y": 2,
                "z": 0
              },
              "orientation": {
                "x": 0,
                "y": 0,
                "z": 0,
                "w": 1
              },
              "scale": {
                "x": 1,
                "y": 1,
                "z": 1
              },
              "visible": true,
              "layer": 0,
              "prefab": null
            },
            {
              "id": "16",
              "name": "Water",
              "children": [],
              "components": [
                {
                  "type": "TileMapRenderer",
                  "config": {
                    "tileMapAssetId": "117",
                    "tileSetAssetId": null,
                    "castShadow": false,
                    "receiveShadow": false,
                    "materialType": "basic",
                    "shaderAssetId": null
                  },
                  "id": "0"
                }
              ],
              "position": {
                "x": 0,
                "y": -2,
                "z": 0
              },
              "orientation": {
                "x": 0,
                "y": 0,
                "z": 0,
                "w": 1
              },
              "scale": {
                "x": 1,
                "y": 1,
                "z": 1
              },
              "visible": true,
              "layer": 0,
              "prefab": null
            },
            {
              "id": "17",
              "name": "Water",
              "children": [],
              "components": [
                {
                  "type": "TileMapRenderer",
                  "config": {
                    "tileMapAssetId": "117",
                    "tileSetAssetId": null,
                    "castShadow": false,
                    "receiveShadow": false,
                    "materialType": "basic",
                    "shaderAssetId": null
                  },
                  "id": "0"
                }
              ],
              "position": {
                "x": 0,
                "y": -4,
                "z": 0
              },
              "orientation": {
                "x": 0,
                "y": 0,
                "z": 0,
                "w": 1
              },
              "scale": {
                "x": 1,
                "y": 1,
                "z": 1
              },
              "visible": true,
              "layer": 0,
              "prefab": null
            },
            {
              "id": "18",
              "name": "Water",
              "children": [],
              "components": [
                {
                  "type": "TileMapRenderer",
                  "config": {
                    "tileMapAssetId": "117",
                    "tileSetAssetId": null,
                    "castShadow": false,
                    "receiveShadow": false,
                    "materialType": "basic",
                    "shaderAssetId": null
                  },
                  "id": "0"
                }
              ],
              "position": {
                "x": 0,
                "y": -6,
                "z": 0
              },
              "orientation": {
                "x": 0,
                "y": 0,
                "z": 0,
                "w": 1
              },
              "scale": {
                "x": 1,
                "y": 1,
                "z": 1
              },
              "visible": true,
              "layer": 0,
              "prefab": null
            }
          ],
          "components": [],
          "position": {
            "x": 4,
            "y": 0,
            "z": 0
          },
          "orientation": {
            "x": 0,
            "y": 0,
            "z": 0,
            "w": 1
          },
          "scale": {
            "x": 1,
            "y": 1,
            "z": 1
          },
          "visible": true,
          "layer": 0,
          "prefab": null
        },
        {
          "id": "19",
          "name": "Column",
          "children": [
            {
              "id": "20",
              "name": "Water",
              "children": [],
              "components": [
                {
                  "type": "TileMapRenderer",
                  "config": {
                    "tileMapAssetId": "117",
                    "tileSetAssetId": null,
                    "castShadow": false,
                    "receiveShadow": false,
                    "materialType": "basic",
                    "shaderAssetId": null
                  },
                  "id": "0"
                }
              ],
              "position": {
                "x": 0,
                "y": 0,
                "z": 0
              },
              "orientation": {
                "x": 0,
                "y": 0,
                "z": 0,
                "w": 1
              },
              "scale": {
                "x": 1,
                "y": 1,
                "z": 1
              },
              "visible": true,
              "layer": 0,
              "prefab": null
            },
            {
              "id": "21",
              "name": "Water1",
              "children": [],
              "components": [
                {
                  "type": "TileMapRenderer",
                  "config": {
                    "tileMapAssetId": "118",
                    "tileSetAssetId": null,
                    "castShadow": false,
                    "receiveShadow": false,
                    "materialType": "basic",
                    "shaderAssetId": null
                  },
                  "id": "0"
                }
              ],
              "position": {
                "x": 0,
                "y": 2,
                "z": 0
              },
              "orientation": {
                "x": 0,
                "y": 0,
                "z": 0,
                "w": 1
              },
              "scale": {
                "x": 1,
                "y": 1,
                "z": 1
              },
              "visible": true,
              "layer": 0,
              "prefab": null
            },
            {
              "id": "22",
              "name": "Water",
              "children": [],
              "components": [
                {
                  "type": "TileMapRenderer",
                  "config": {
                    "tileMapAssetId": "117",
                    "tileSetAssetId": null,
                    "castShadow": false,
                    "receiveShadow": false,
                    "materialType": "basic",
                    "shaderAssetId": null
                  },
                  "id": "0"
                }
              ],
              "position": {
                "x": 0,
                "y": -2,
                "z": 0
              },
              "orientation": {
                "x": 0,
                "y": 0,
                "z": 0,
                "w": 1
              },
              "scale": {
                "x": 1,
                "y": 1,
                "z": 1
              },
              "visible": true,
              "layer": 0,
              "prefab": null
            },
            {
              "id": "23",
              "name": "Water",
              "children": [],
              "components": [
                {
                  "type": "TileMapRenderer",
                  "config": {
                    "tileMapAssetId": "117",
                    "tileSetAssetId": null,
                    "castShadow": false,
                    "receiveShadow": false,
                    "materialType": "basic",
                    "shaderAssetId": null
                  },
                  "id": "0"
                }
              ],
              "position": {
                "x": 0,
                "y": -4,
                "z": 0
              },
              "orientation": {
                "x": 0,
                "y": 0,
                "z": 0,
                "w": 1
              },
              "scale": {
                "x": 1,
                "y": 1,
                "z": 1
              },
              "visible": true,
              "layer": 0,
              "prefab": null
            },
            {
              "id": "24",
              "name": "Water",
              "children": [],
              "components": [
                {
                  "type": "TileMapRenderer",
                  "config": {
                    "tileMapAssetId": "117",
                    "tileSetAssetId": null,
                    "castShadow": false,
                    "receiveShadow": false,
                    "materialType": "basic",
                    "shaderAssetId": null
                  },
                  "id": "0"
                }
              ],
              "position": {
                "x": 0,
                "y": -6,
                "z": 0
              },
              "orientation": {
                "x": 0,
                "y": 0,
                "z": 0,
                "w": 1
              },
              "scale": {
                "x": 1,
                "y": 1,
                "z": 1
              },
              "visible": true,
              "layer": 0,
              "prefab": null
            }
          ],
          "components": [],
          "position": {
            "x": 6,
            "y": 0,
            "z": 0
          },
          "orientation": {
            "x": 0,
            "y": 0,
            "z": 0,
            "w": 1
          },
          "scale": {
            "x": 1,
            "y": 1,
            "z": 1
          },
          "visible": true,
          "layer": 0,
          "prefab": null
        },
        {
          "id": "25",
          "name": "Column",
          "children": [
            {
              "id": "26",
              "name": "Water",
              "children": [],
              "components": [
                {
                  "type": "TileMapRenderer",
                  "config": {
                    "tileMapAssetId": "117",
                    "tileSetAssetId": null,
                    "castShadow": false,
                    "receiveShadow": false,
                    "materialType": "basic",
                    "shaderAssetId": null
                  },
                  "id": "0"
                }
              ],
              "position": {
                "x": 0,
                "y": 0,
                "z": 0
              },
              "orientation": {
                "x": 0,
                "y": 0,
                "z": 0,
                "w": 1
              },
              "scale": {
                "x": 1,
                "y": 1,
                "z": 1
              },
              "visible": true,
              "layer": 0,
              "prefab": null
            },
            {
              "id": "27",
              "name": "Water1",
              "children": [],
              "components": [
                {
                  "type": "TileMapRenderer",
                  "config": {
                    "tileMapAssetId": "118",
                    "tileSetAssetId": null,
                    "castShadow": false,
                    "receiveShadow": false,
                    "materialType": "basic",
                    "shaderAssetId": null
                  },
                  "id": "0"
                }
              ],
              "position": {
                "x": 0,
                "y": 2,
                "z": 0
              },
              "orientation": {
                "x": 0,
                "y": 0,
                "z": 0,
                "w": 1
              },
              "scale": {
                "x": 1,
                "y": 1,
                "z": 1
              },
              "visible": true,
              "layer": 0,
              "prefab": null
            },
            {
              "id": "28",
              "name": "Water",
              "children": [],
              "components": [
                {
                  "type": "TileMapRenderer",
                  "config": {
                    "tileMapAssetId": "117",
                    "tileSetAssetId": null,
                    "castShadow": false,
                    "receiveShadow": false,
                    "materialType": "basic",
                    "shaderAssetId": null
                  },
                  "id": "0"
                }
              ],
              "position": {
                "x": 0,
                "y": -2,
                "z": 0
              },
              "orientation": {
                "x": 0,
                "y": 0,
                "z": 0,
                "w": 1
              },
              "scale": {
                "x": 1,
                "y": 1,
                "z": 1
              },
              "visible": true,
              "layer": 0,
              "prefab": null
            },
            {
              "id": "29",
              "name": "Water",
              "children": [],
              "components": [
                {
                  "type": "TileMapRenderer",
                  "config": {
                    "tileMapAssetId": "117",
                    "tileSetAssetId": null,
                    "castShadow": false,
                    "receiveShadow": false,
                    "materialType": "basic",
                    "shaderAssetId": null
                  },
                  "id": "0"
                }
              ],
              "position": {
                "x": 0,
                "y": -4,
                "z": 0
              },
              "orientation": {
                "x": 0,
                "y": 0,
                "z": 0,
                "w": 1
              },
              "scale": {
                "x": 1,
                "y": 1,
                "z": 1
              },
              "visible": true,
              "layer": 0,
              "prefab": null
            },
            {
              "id": "30",
              "name": "Water",
              "children": [],
              "components": [
                {
                  "type": "TileMapRenderer",
                  "config": {
                    "tileMapAssetId": "117",
                    "tileSetAssetId": null,
                    "castShadow": false,
                    "receiveShadow": false,
                    "materialType": "basic",
                    "shaderAssetId": null
                  },
                  "id": "0"
                }
              ],
              "position": {
                "x": 0,
                "y": -6,
                "z": 0
              },
              "orientation": {
                "x": 0,
                "y": 0,
                "z": 0,
                "w": 1
              },
              "scale": {
                "x": 1,
                "y": 1,
                "z": 1
              },
              "visible": true,
              "layer": 0,
              "prefab": null
            }
          ],
          "components": [],
          "position": {
            "x": 8,
            "y": 0,
            "z": 0
          },
          "orientation": {
            "x": 0,
            "y": 0,
            "z": 0,
            "w": 1
          },
          "scale": {
            "x": 1,
            "y": 1,
            "z": 1
          },
          "visible": true,
          "layer": 0,
          "prefab": null
        },
        {
          "id": "31",
          "name": "Column",
          "children": [
            {
              "id": "32",
              "name": "Water",
              "children": [],
              "components": [
                {
                  "type": "TileMapRenderer",
                  "config": {
                    "tileMapAssetId": "117",
                    "tileSetAssetId": null,
                    "castShadow": false,
                    "receiveShadow": false,
                    "materialType": "basic",
                    "shaderAssetId": null
                  },
                  "id": "0"
                }
              ],
              "position": {
                "x": 0,
                "y": 0,
                "z": 0
              },
              "orientation": {
                "x": 0,
                "y": 0,
                "z": 0,
                "w": 1
              },
              "scale": {
                "x": 1,
                "y": 1,
                "z": 1
              },
              "visible": true,
              "layer": 0,
              "prefab": null
            },
            {
              "id": "33",
              "name": "Water1",
              "children": [],
              "components": [
                {
                  "type": "TileMapRenderer",
                  "config": {
                    "tileMapAssetId": "118",
                    "tileSetAssetId": null,
                    "castShadow": false,
                    "receiveShadow": false,
                    "materialType": "basic",
                    "shaderAssetId": null
                  },
                  "id": "0"
                }
              ],
              "position": {
                "x": 0,
                "y": 2,
                "z": 0
              },
              "orientation": {
                "x": 0,
                "y": 0,
                "z": 0,
                "w": 1
              },
              "scale": {
                "x": 1,
                "y": 1,
                "z": 1
              },
              "visible": true,
              "layer": 0,
              "prefab": null
            },
            {
              "id": "34",
              "name": "Water",
              "children": [],
              "components": [
                {
                  "type": "TileMapRenderer",
                  "config": {
                    "tileMapAssetId": "117",
                    "tileSetAssetId": null,
                    "castShadow": false,
                    "receiveShadow": false,
                    "materialType": "basic",
                    "shaderAssetId": null
                  },
                  "id": "0"
                }
              ],
              "position": {
                "x": 0,
                "y": -2,
                "z": 0
              },
              "orientation": {
                "x": 0,
                "y": 0,
                "z": 0,
                "w": 1
              },
              "scale": {
                "x": 1,
                "y": 1,
                "z": 1
              },
              "visible": true,
              "layer": 0,
              "prefab": null
            },
            {
              "id": "35",
              "name": "Water",
              "children": [],
              "components": [
                {
                  "type": "TileMapRenderer",
                  "config": {
                    "tileMapAssetId": "117",
                    "tileSetAssetId": null,
                    "castShadow": false,
                    "receiveShadow": false,
                    "materialType": "basic",
                    "shaderAssetId": null
                  },
                  "id": "0"
                }
              ],
              "position": {
                "x": 0,
                "y": -4,
                "z": 0
              },
              "orientation": {
                "x": 0,
                "y": 0,
                "z": 0,
                "w": 1
              },
              "scale": {
                "x": 1,
                "y": 1,
                "z": 1
              },
              "visible": true,
              "layer": 0,
              "prefab": null
            },
            {
              "id": "36",
              "name": "Water",
              "children": [],
              "components": [
                {
                  "type": "TileMapRenderer",
                  "config": {
                    "tileMapAssetId": "117",
                    "tileSetAssetId": null,
                    "castShadow": false,
                    "receiveShadow": false,
                    "materialType": "basic",
                    "shaderAssetId": null
                  },
                  "id": "0"
                }
              ],
              "position": {
                "x": 0,
                "y": -6,
                "z": 0
              },
              "orientation": {
                "x": 0,
                "y": 0,
                "z": 0,
                "w": 1
              },
              "scale": {
                "x": 1,
                "y": 1,
                "z": 1
              },
              "visible": true,
              "layer": 0,
              "prefab": null
            }
          ],
          "components": [],
          "position": {
            "x": 10,
            "y": 0,
            "z": 0
          },
          "orientation": {
            "x": 0,
            "y": 0,
            "z": 0,
            "w": 1
          },
          "scale": {
            "x": 1,
            "y": 1,
            "z": 1
          },
          "visible": true,
          "layer": 0,
          "prefab": null
        }
      ],
      "components": [],
      "position": {
        "x": 0,
        "y": 0,
        "z": 0
      },
      "orientation": {
        "x": 0,
        "y": 0,
        "z": 0,
        "w": 1
      },
      "scale": {
        "x": 0.5,
        "y": 0.5,
        "z": 1
      },
      "visible": true,
      "layer": 0,
      "prefab": null
    }
  ]
}